{
    "Icewind Dale Trinkets": [
        {
            "Dice Number": "1-4",
            "Trinket": "A small wooden figurine of a yawning walrus, painted in red and black"
        },
        {
            "Dice Number": "5-8",
            "Trinket": "A pair of scrimshaw cufflinks with an image of a fisherman on a boat engraved on them"
        },
        {
            "Dice Number": "9-12",
            "Trinket": "A small iron key with a frayed blue and gold cord tied to it"
        },
        {
            "Dice Number": "13-16",
            "Trinket": "A small illustrated book of Northlander myths that has pages missing"
        },
        {
            "Dice Number": "17-20",
            "Trinket": "A damaged scrimshaw cameo depicting a merfolk"
        },
        {
            "Dice Number": "21-24",
            "Trinket": "A stone from a burial cairn with a tiny Dwarvish rune carved into it"
        },
        {
            "Dice Number": "25-28",
            "Trinket": "A ripped cloth sail with a symbol you don't recognize"
        },
        {
            "Dice Number": "29-32",
            "Trinket": "An Ulu knife with a scrimshaw handle"
        },
        {
            "Dice Number": "33-36",
            "Trinket": "A jar containing an unidentifiable, sweet, sticky substance"
        },
        {
            "Dice Number": "37-40",
            "Trinket": "A delicate glass ball painted with snowflakes, capped by a metal loop with a tiny hook attached to it"
        },
        {
            "Dice Number": "41-44",
            "Trinket": "An expedition log with missing pages and a pressed flower used as a bookmark"
        },
        {
            "Dice Number": "45-48",
            "Trinket": "An owl figurine carved from whalebone"
        },
        {
            "Dice Number": "49-52",
            "Trinket": "A sewing box that smells of old wood and has three spools of blue thread inside"
        },
        {
            "Dice Number": "53-56",
            "Trinket": "A scrimshaw-handled ink pen with black runic designs along its length"
        },
        {
            "Dice Number": "57-60",
            "Trinket": "A brooch made from a small insect encased in amber"
        },
        {
            "Dice Number": "61-64",
            "Trinket": "A scrimshaw pepper shaker etched with the letter W"
        },
        {
            "Dice Number": "65-68",
            "Trinket": "An old, wooden-handled ice pick stained with blood that won't wash off"
        },
        {
            "Dice Number": "69-72",
            "Trinket": "A fabric doll bearing an angry expression"
        },
        {
            "Dice Number": "73-76",
            "Trinket": "A set of wind chimes made from seashells"
        },
        {
            "Dice Number": "77-80",
            "Trinket": "A beautiful silver tin that, when opened, emits the smell of rotting fish"
        },
        {
            "Dice Number": "81-84",
            "Trinket": "A bloodstained dreamcatcher made from fishing line, gold wire, and snowy owlbear feathers"
        },
        {
            "Dice Number": "85-88",
            "Trinket": "A figurine of a polar bear made of ice that never melts"
        },
        {
            "Dice Number": "89-92",
            "Trinket": "A snow globe that doesn't need to be shaken"
        },
        {
            "Dice Number": "93-96",
            "Trinket": "A piece of sea glass shaped like a unicorn's horn"
        },
        {
            "Dice Number": "97-100",
            "Trinket": "A dark blue scarf that gets lighter in shade the higher the altitude of the wearer"
        }
    ]
}
